<?xml version='1.0' encoding='UTF-8'?>
<types:mule xmlns:types="http://www.mulesoft.org/schema/mule/types">
  <types:catalog>
    <types:type name="auto_381bd706-40f5-4c97-87ba-d733a8b67770_Output-Attributes" format="java">
      <types:shape format="weave" example="weave/autogenerated/381bd706-40f5-4c97-87ba-d733a8b67770/Output-Attributes.wev" autogeneratedOrigin="70ed4460-0ef2-4e9f-9bef-fc57fee1b70b"><![CDATA[%dw 2.0

type auto_381bd706_40f5_4c97_87ba_d733a8b67770_Output_Attributes = {|
  listenerPath: String, 
  rawRequestPath: String, 
  relativePath: String, 
  maskedRequestPath: String, 
  version: String, 
  scheme: String, 
  method: String, 
  requestUri: String, 
  rawRequestUri: String, 
  queryString: String, 
  localAddress: String, 
  remoteAddress: String, 
  clientCertificate?: java_security_cert_Certificate, 
  queryParams: { _?: String }, 
  uriParams: { _?: String }, 
  requestPath: String, 
  headers: { _?: String }
|} {"typeAlias": "HttpRequestAttributes",
"typeId": "org.mule.extension.http.api.HttpRequestAttributes"}
type java_security_cert_Certificate = {|
  encoded?: Binary, 
  publicKey?: java_security_PublicKey, 
  "type"?: String
|} {"typeAlias": "Certificate",
"typeId": "java.security.cert.Certificate"}
type java_security_PublicKey = {|  |} {"typeAlias": "PublicKey",
"typeId": "java.security.PublicKey"}





]]></types:shape>
    </types:type>
    <types:type name="auto_8ed91712-c828-4e23-9bb4-0cafcff796b7_Input-Variables-medicalCategories" format="java">
      <types:shape format="weave" example="weave/autogenerated/8ed91712-c828-4e23-9bb4-0cafcff796b7/Input-Variables-medicalCategories.wev" autogeneratedOrigin="7e6db404-0f10-4e68-8303-f3e535744d31"><![CDATA[%dw 2.0

type auto_8ed91712_c828_4e23_9bb4_0cafcff796b7_Input_Variables_medicalCategories = Any

]]></types:shape>
    </types:type>
    <types:type name="auto_8ed91712-c828-4e23-9bb4-0cafcff796b7_Output-Payload" format="json">
      <types:shape format="weave" example="weave/autogenerated/8ed91712-c828-4e23-9bb4-0cafcff796b7/Output-Payload.wev" autogeneratedOrigin="7e6db404-0f10-4e68-8303-f3e535744d31"><![CDATA[%dw 2.0

type auto_8ed91712_c828_4e23_9bb4_0cafcff796b7_Output_Payload = {|
  name: String, 
  hospital: String, 
  category: String, 
  availability: String, 
  fee: String
|}

]]></types:shape>
    </types:type>
    <types:type name="auto_8ed91712-c828-4e23-9bb4-0cafcff796b7_Output-Attributes" format="java">
      <types:shape format="weave" example="weave/autogenerated/8ed91712-c828-4e23-9bb4-0cafcff796b7/Output-Attributes.wev" autogeneratedOrigin="7e6db404-0f10-4e68-8303-f3e535744d31"><![CDATA[%dw 2.0

type auto_8ed91712_c828_4e23_9bb4_0cafcff796b7_Output_Attributes = {|
  listenerPath: String, 
  rawRequestPath: String, 
  relativePath: String, 
  maskedRequestPath: String, 
  version: String, 
  scheme: String, 
  method: String, 
  requestUri: String, 
  rawRequestUri: String, 
  queryString: String, 
  localAddress: String, 
  remoteAddress: String, 
  clientCertificate?: java_security_cert_Certificate, 
  queryParams: { _?: String }, 
  uriParams: { _?: String }, 
  requestPath: String, 
  headers: { _?: String }
|} {"typeAlias": "HttpRequestAttributes",
"typeId": "org.mule.extension.http.api.HttpRequestAttributes"}
type java_security_cert_Certificate = {|
  encoded?: Binary, 
  publicKey?: java_security_PublicKey, 
  "type"?: String
|} {"typeAlias": "Certificate",
"typeId": "java.security.cert.Certificate"}
type java_security_PublicKey = {|  |} {"typeAlias": "PublicKey",
"typeId": "java.security.PublicKey"}





]]></types:shape>
    </types:type>
    <types:type name="auto_8ed91712-c828-4e23-9bb4-0cafcff796b7_Output-Variables-medicalCategories" format="java">
      <types:shape format="weave" example="weave/autogenerated/8ed91712-c828-4e23-9bb4-0cafcff796b7/Output-Variables-medicalCategories.wev" autogeneratedOrigin="7e6db404-0f10-4e68-8303-f3e535744d31"><![CDATA[%dw 2.0

type auto_8ed91712_c828_4e23_9bb4_0cafcff796b7_Output_Variables_medicalCategories = Any

]]></types:shape>
    </types:type>
    <types:type name="auto_7e4a5f58-6ea9-4613-943f-623fe37007fd_Output-Payload" format="java">
      <types:shape format="weave" example="weave/autogenerated/7e4a5f58-6ea9-4613-943f-623fe37007fd/Output-Payload.wev" autogeneratedOrigin="7efc0a0c-f8de-43ab-bcc6-b462df5ab483"><![CDATA[%dw 2.0

type auto_7e4a5f58_6ea9_4613_943f_623fe37007fd_Output_Payload = Array<"Mulesoft" | "Cristiano Ronaldo" | "Bill Gates" | "Nelson Dias">

]]></types:shape>
    </types:type>
    <types:type name="auto_7e4a5f58-6ea9-4613-943f-623fe37007fd_Output-Attributes" format="java">
      <types:shape format="weave" example="weave/autogenerated/7e4a5f58-6ea9-4613-943f-623fe37007fd/Output-Attributes.wev" autogeneratedOrigin="7efc0a0c-f8de-43ab-bcc6-b462df5ab483"><![CDATA[%dw 2.0

type auto_7e4a5f58_6ea9_4613_943f_623fe37007fd_Output_Attributes = {|
  listenerPath: String, 
  rawRequestPath: String, 
  relativePath: String, 
  maskedRequestPath: String, 
  version: String, 
  scheme: String, 
  method: String, 
  requestUri: String, 
  rawRequestUri: String, 
  queryString: String, 
  localAddress: String, 
  remoteAddress: String, 
  clientCertificate?: java_security_cert_Certificate, 
  queryParams: { _?: String }, 
  uriParams: { _?: String }, 
  requestPath: String, 
  headers: { _?: String }
|} {"typeAlias": "HttpRequestAttributes",
"typeId": "org.mule.extension.http.api.HttpRequestAttributes"}
type java_security_cert_Certificate = {|
  encoded?: Binary, 
  publicKey?: java_security_PublicKey, 
  "type"?: String
|} {"typeAlias": "Certificate",
"typeId": "java.security.cert.Certificate"}
type java_security_PublicKey = {|  |} {"typeAlias": "PublicKey",
"typeId": "java.security.PublicKey"}





]]></types:shape>
    </types:type>
  </types:catalog>
  <types:enrichment select="#381bd706-40f5-4c97-87ba-d733a8b67770">
    <types:processor-declaration>
      <types:output-event>
        <types:message>
          <types:attributes type="auto_381bd706-40f5-4c97-87ba-d733a8b67770_Output-Attributes"/>
        </types:message>
      </types:output-event>
    </types:processor-declaration>
  </types:enrichment>
  <types:enrichment select="#8ed91712-c828-4e23-9bb4-0cafcff796b7">
    <types:processor-declaration>
      <types:input-event>
        <types:variables>
          <types:variable name="medicalCategories" type="auto_8ed91712-c828-4e23-9bb4-0cafcff796b7_Input-Variables-medicalCategories"/>
        </types:variables>
      </types:input-event>
      <types:output-event>
        <types:message>
          <types:payload type="auto_8ed91712-c828-4e23-9bb4-0cafcff796b7_Output-Payload"/>
          <types:attributes type="auto_8ed91712-c828-4e23-9bb4-0cafcff796b7_Output-Attributes"/>
        </types:message>
        <types:variables>
          <types:variable name="medicalCategories" type="auto_8ed91712-c828-4e23-9bb4-0cafcff796b7_Output-Variables-medicalCategories"/>
        </types:variables>
      </types:output-event>
    </types:processor-declaration>
  </types:enrichment>
  <types:enrichment select="#7e4a5f58-6ea9-4613-943f-623fe37007fd">
    <types:processor-declaration>
      <types:output-event>
        <types:message>
          <types:payload type="auto_7e4a5f58-6ea9-4613-943f-623fe37007fd_Output-Payload"/>
          <types:attributes type="auto_7e4a5f58-6ea9-4613-943f-623fe37007fd_Output-Attributes"/>
        </types:message>
      </types:output-event>
    </types:processor-declaration>
  </types:enrichment>
</types:mule>